tensorflowtools/__init__.py
tensorflowtools/kerastools.py
tensorflowtools/hftools/__init__.py
tensorflowtools/hftools/core.py
tensorflowtools/hftools/internal.py
tensorflowtools-2.0.4.dist-info/licenses/LICENSE
tensorflowtools-2.0.4.dist-info/METADATA
tensorflowtools-2.0.4.dist-info/WHEEL
tensorflowtools-2.0.4.dist-info/top_level.txt
tensorflowtools-2.0.4.dist-info/RECORD
