Metadata-Version: 2.4
Name: tensorflowtools
Version: 2.0.4
Summary: A small package with various tensorflow uitlities independent of Tensorflow Addons
Author-email: Rihaan Meher <meherrihaan@gmail.com>
Project-URL: Homepage, https://github.com/sharktide/tftools
Project-URL: Issues, https://github.com/sharktide/tftools/issues
Classifier: Programming Language :: Python :: 3
Classifier: Operating System :: OS Independent
Requires-Python: >=3.9
License-File: LICENSE
Requires-Dist: requests
Requires-Dist: huggingface_hub
Requires-Dist: textfmt
Dynamic: license-file
